sigye/__init__.py
sigye/cli.py
sigye/models.py
sigye/services.py
sigye/config/__init__.py
sigye/config/default_config.yaml
sigye/config/settings.py
sigye/editors/__init__.py
sigye/editors/prompt_editor.py
sigye/editors/shell_editor.py
sigye/editors/tests/__init__.py
sigye/editors/tests/test_editors.py
sigye/output/__init__.py
sigye/output/csv_output.py
sigye/output/json_output.py
sigye/output/markdown_output.py
sigye/output/output.py
sigye/output/output_utils.py
sigye/output/rich_text_output.py
sigye/output/text_output.py
sigye/output/yaml_output.py
sigye/output/tests/__init__.py
sigye/output/tests/test_csv_output.py
sigye/output/tests/test_json_output.py
sigye/output/tests/test_markdown_output.py
sigye/output/tests/test_output.py
sigye/output/tests/test_rich_text_output.py
sigye/output/tests/test_text_output.py
sigye/output/tests/test_utils.py
sigye/output/tests/test_yaml_output.py
sigye/repositories/__init__.py
sigye/repositories/time_entry_repo.py
sigye/repositories/time_entry_repo_file.py
sigye/repositories/time_entry_repo_orm.py
sigye/repositories/tests/__init__.py
sigye/repositories/tests/test_repo_file.py
sigye/repositories/tests/test_repo_orm.py
sigye/tests/__init__.py
sigye/tests/test_cli.py
sigye/tests/test_models.py
sigye/tests/test_services.py
sigye/utils/__init__.py
sigye/utils/datetime_utils.py
sigye/utils/translation.py
sigye/utils/extra/__init__.py
sigye/utils/extra/generator.py
sigye/utils/locale/ko/LC_MESSAGES/messages.mo
sigye/utils/locale/ko/LC_MESSAGES/messages.po
sigye/utils/tests/__init__.py
sigye/utils/tests/test_datetime.py
sigye-0.10.2.dist-info/METADATA
sigye-0.10.2.dist-info/WHEEL
sigye-0.10.2.dist-info/entry_points.txt
sigye-0.10.2.dist-info/licenses/LICENSE
sigye-0.10.2.dist-info/RECORD
