Metadata-Version: 2.4
Name: sigye
Version: 0.10.2
Summary: (시계) A simple command-line program for tracking time.
Project-URL: repository, https://github.com/swilcox/sigye.git
Project-URL: github, https://github.com/swilcox/sigye
Author-email: swilcox <steven@wilcox.be>
License: MIT License
License-File: LICENSE
Requires-Python: >=3.12
Requires-Dist: click-aliases>=1.0.5
Requires-Dist: click-datetime>=0.4.0
Requires-Dist: click>=8.1.7
Requires-Dist: humanize>=4.11.0
Requires-Dist: jinja2>=3.1.5
Requires-Dist: peewee>=3.17.8
Requires-Dist: pydantic-settings>=2.6.1
Requires-Dist: pydantic>=2.9.2
Requires-Dist: rich>=13.9.4
Requires-Dist: rtoml>=0.13.0
Requires-Dist: ryaml>=0.4.0
